LICENSE
MANIFEST.in
README.rst
setup.py
sphinx_nameko_mw_theme/__init__.py
sphinx_nameko_mw_theme.egg-info/PKG-INFO
sphinx_nameko_mw_theme.egg-info/SOURCES.txt
sphinx_nameko_mw_theme.egg-info/dependency_links.txt
sphinx_nameko_mw_theme.egg-info/entry_points.txt
sphinx_nameko_mw_theme.egg-info/not-zip-safe
sphinx_nameko_mw_theme.egg-info/requires.txt
sphinx_nameko_mw_theme.egg-info/top_level.txt
sphinx_nameko_mw_theme/nameko-mw/layout.html
sphinx_nameko_mw_theme/nameko-mw/reference.html
sphinx_nameko_mw_theme/nameko-mw/relations.html
sphinx_nameko_mw_theme/nameko-mw/relbar.html
sphinx_nameko_mw_theme/nameko-mw/theme.conf
sphinx_nameko_mw_theme/nameko-mw/static/nameko-mw.css_t
sphinx_nameko_mw_theme/nameko-mw/static/pygments.css