Metadata-Version: 1.1
Name: sphinx-nameko-mw-theme
Version: 0.0.8
Summary: Sphinx Nameko MW Theme
Home-page: https://github.com/penseleit/sphinx-nameko-mw-theme
Author: penseleit
Author-email: penseleit@mediaware.com.au
License: MIT
Platform: UNKNOWN
Classifier: Intended Audience :: Developers
Classifier: License :: OSI Approved :: MIT License
Classifier: Natural Language :: English
Classifier: Operating System :: OS Independent
Classifier: Programming Language :: Python
Classifier: Topic :: Internet
Classifier: Topic :: Software Development :: Documentation
